pockets/__init__.py
pockets/_version.py
pockets/autolog.py
pockets/collections.py
pockets/datetime.py
pockets/decorators.py
pockets/inspect.py
pockets/iterators.py
pockets/logging.py
pockets/string.py
pockets-0.9.dist-info/AUTHORS
pockets-0.9.dist-info/LICENSE
pockets-0.9.dist-info/METADATA
pockets-0.9.dist-info/WHEEL
pockets-0.9.dist-info/top_level.txt
pockets-0.9.dist-info/zip-safe
pockets-0.9.dist-info/RECORD
