Metadata-Version: 2.1
Name: pockets
Version: 0.9
Summary: A collection of helpful Python tools!
Home-page: http://pockets.readthedocs.org
Author: Rob Ruana
Author-email: rob@robruana.com
License: BSD
Download-URL: http://pypi.python.org/pypi/pockets
Platform: any
Classifier: Development Status :: 5 - Production/Stable
Classifier: Environment :: Console
Classifier: Environment :: Web Environment
Classifier: Intended Audience :: Developers
Classifier: License :: OSI Approved :: BSD License
Classifier: Operating System :: OS Independent
Classifier: Programming Language :: Python
Classifier: Programming Language :: Python :: 2
Classifier: Programming Language :: Python :: 3
Classifier: Topic :: Utilities
Classifier: Topic :: Software Development :: Libraries
Classifier: Topic :: Software Development :: Libraries :: Python Modules
Requires-Dist: six (>=1.5.2)
